Labs/design.v
module and_gate (
    input a,
    input b,
    input c,
    output reg sum,carry 

);
always @(*)
begin
  
sum = a^b^c;
 carry= (a &b) | (( a ^b) & c);
 end
 
endmodule

Labs/testbench.v
`timescale 1ns/1ps

module tb_and_gate;

    reg a, b, c;
    wire sum, carry;

    // Instantiate DUT
    and_gate uut (
        .a(a),
        .b(b),
        .c(c),
        .sum(sum),
        .carry(carry)
    );

    initial begin
        $dumpfile("wave1.vcd");   // for waveform
        $dumpvars(0, tb_and_gate);

        $monitor("Time=%0t | a=%b b=%b c=%b | sum=%b carry=%b",
                  $time, a, b, c, sum, carry);

        a=0; b=0; c=0; #10;
        a=0; b=0; c=1; #10;
        a=0; b=1; c=0; #10;
        a=0; b=1; c=1; #10;
        a=1; b=0; c=0; #10;
        a=1; b=0; c=1; #10;
        a=1; b=1; c=0; #10;
        a=1; b=1; c=1; #10;

        $finish;
    end

endmodule

wave1.vcd
$date
	Thu May  7 22:59:32 2026
$end
$version
	Icarus Verilog
$end
$timescale
	1ps
$end
$scope module tb_and_gate $end
$var wire 1 ! sum $end
$var wire 1 " carry $end
$var reg 1 # a $end
$var reg 1 $ b $end
$var reg 1 % c $end
$scope module uut $end
$var wire 1 # a $end
$var wire 1 $ b $end
$var wire 1 % c $end
$var reg 1 " carry $end
$var reg 1 ! sum $end
$upscope $end
$upscope $end
$enddefinitions $end
$comment Show the parameter values. $end
$dumpall
$end
#0
$dumpvars
0%
0$
0#
0"
0!
$end
#10000
1!
1%
#20000
0%
1$
#30000
1"
0!
1%
#40000
0"
1!
0%
0$
1#
#50000
1"
0!
1%
#60000
0%
1$
#70000
1!
1%
