Labs/data_memory.v
`timescale 1ns / 1ps

module data_memory(
    input clk,
    input MemWrite,
    input MemRead,
    input [31:0] address,
    input [31:0] write_data,
    output reg [31:0] read_data
);

// Memory (32 words)
reg [31:0] memory [0:31];

// Write & Read operations
always @(posedge clk)
begin
    if (MemWrite)
        memory[address] <= write_data;

    if (MemRead)
        read_data <= memory[address];
end

endmodule

Labs/data_memory_tb.v
`timescale 1ns / 1ps

module data_memory_tb;

reg clk;
reg MemWrite;
reg MemRead;
reg [31:0] address;
reg [31:0] write_data;
wire [31:0] read_data;

// Instantiate
data_memory uut (
    .clk(clk),
    .MemWrite(MemWrite),
    .MemRead(MemRead),
    .address(address),
    .write_data(write_data),
    .read_data(read_data)
);

// Clock
always #1 clk = ~clk;

initial
begin
    $dumpfile("data_mem.vcd");
    $dumpvars(0, data_memory_tb);

    clk = 0;
    MemWrite = 0;
    MemRead = 0;

    // WRITE DATA
    #20 MemWrite = 1; address = 5; write_data = 32'hAABBCCDD;
    #20 address = 10; write_data = 32'h12345678;

    #20 MemWrite = 0;

    // READ DATA
    #20 MemRead = 1; address = 5;
    #20 address = 10;

    #40 $finish;
end

initial
begin
    $monitor("Time=%0t | Addr=%d | Write=%h | Read=%h", 
              $time, address, write_data, read_data);
end

endmodule

Labs/data_mem.vcd
$date
	Thu Apr  2 10:59:45 2026
$end
$version
	Icarus Verilog
$end
$timescale
	1ps
$end
$scope module data_memory_tb $end
$var wire 32 ! read_data [31:0] $end
$var reg 1 " MemRead $end
$var reg 1 # MemWrite $end
$var reg 32 $ address [31:0] $end
$var reg 1 % clk $end
$var reg 32 & write_data [31:0] $end
$scope module uut $end
$var wire 1 " MemRead $end
$var wire 1 # MemWrite $end
$var wire 32 ' address [31:0] $end
$var wire 1 % clk $end
$var wire 32 ( write_data [31:0] $end
$var reg 32 ) read_data [31:0] $end
$upscope $end
$upscope $end
$enddefinitions $end
$comment Show the parameter values. $end
$dumpall
$end
#0
$dumpvars
bx )
bx (
bx '
bx &
0%
bx $
0#
0"
bx !
$end
#1000
1%
#2000
0%
#3000
1%
#4000
0%
#5000
1%
#6000
0%
#7000
1%
#8000
0%
#9000
1%
#10000
0%
#11000
1%
#12000
0%
#13000
1%
#14000
0%
#15000
1%
#16000
0%
#17000
1%
#18000
0%
#19000
1%
#20000
0%
b10101010101110111100110011011101 &
b10101010101110111100110011011101 (
b101 $
b101 '
1#
#21000
1%
#22000
0%
#23000
1%
#24000
0%
#25000
1%
#26000
0%
#27000
1%
#28000
0%
#29000
1%
#30000
0%
#31000
1%
#32000
0%
#33000
1%
#34000
0%
#35000
1%
#36000
0%
#37000
1%
#38000
0%
#39000
1%
#40000
0%
b10010001101000101011001111000 &
b10010001101000101011001111000 (
b1010 $
b1010 '
#41000
1%
#42000
0%
#43000
1%
#44000
0%
#45000
1%
#46000
0%
#47000
1%
#48000
0%
#49000
1%
#50000
0%
#51000
1%
#52000
0%
#53000
1%
#54000
0%
#55000
1%
#56000
0%
#57000
1%
#58000
0%
#59000
1%
#60000
0%
0#
#61000
1%
#62000
0%
#63000
1%
#64000
0%
#65000
1%
#66000
0%
#67000
1%
#68000
0%
#69000
1%
#70000
0%
#71000
1%
#72000
0%
#73000
1%
#74000
0%
#75000
1%
#76000
0%
#77000
1%
#78000
0%
#79000
1%
#80000
0%
b101 $
b101 '
1"
#81000
b10101010101110111100110011011101 !
b10101010101110111100110011011101 )
1%
#82000
0%
#83000
1%
#84000
0%
#85000
1%
#86000
0%
#87000
1%
#88000
0%
#89000
1%
#90000
0%
#91000
1%
#92000
0%
#93000
1%
#94000
0%
#95000
1%
#96000
0%
#97000
1%
#98000
0%
#99000
1%
#100000
0%
b1010 $
b1010 '
#101000
b10010001101000101011001111000 !
b10010001101000101011001111000 )
1%
