Labs/inst_mem.v
`timescale 1ns / 1ps

module inst_mem(
    input [31:0] PC,
    input reset,   // (kept for compatibility, not used now)
    output [31:0] Instruction_Code
);

reg [7:0] Memory [31:0]; // Byte-addressable memory (32 bytes)

// Fetch instruction (Little Endian)
assign Instruction_Code = {Memory[PC+3], Memory[PC+2], Memory[PC+1], Memory[PC]};

// Initialize memory ONCE at simulation start
initial
begin
    // add t1, s0, s1
    Memory[3]  = 8'h00;
    Memory[2]  = 8'h94;
    Memory[1]  = 8'h03;
    Memory[0]  = 8'h33;

    // sub t2, s2, s3
    Memory[7]  = 8'h41;
    Memory[6]  = 8'h39;
    Memory[5]  = 8'h03;
    Memory[4]  = 8'hb3;

    // mul t0, s4, s5
    Memory[11] = 8'h03;
    Memory[10] = 8'h5a;
    Memory[9]  = 8'h02;
    Memory[8]  = 8'hb3;

    // xor t3, s6, s7
    Memory[15] = 8'h01;
    Memory[14] = 8'h7b;
    Memory[13] = 8'h4e;
    Memory[12] = 8'h33;

    // sll t4, s8, s9
    Memory[19] = 8'h01;
    Memory[18] = 8'h9c;
    Memory[17] = 8'h1e;
    Memory[16] = 8'hb3;

    // srl t5, s10, s11
    Memory[23] = 8'h01;
    Memory[22] = 8'hbd;
    Memory[21] = 8'h5f;
    Memory[20] = 8'h33;

    // and t6, a2, a3
    Memory[27] = 8'h00;
    Memory[26] = 8'hd6;
    Memory[25] = 8'h7f;
    Memory[24] = 8'hb3;

    // or a7, a4, a5
    Memory[31] = 8'h00;
    Memory[30] = 8'hf7;
    Memory[29] = 8'h68;
    Memory[28] = 8'hb3;
end

endmodule

Labs/adder.v
`timescale 1ns / 1ps

module adder(
    input [31:0] a,
    input [31:0] b,
    output [31:0] sum
);

assign sum = a + b;

endmodule

Labs/PC.v
`timescale 1ns / 1ps

module PC(
    input clk,
    input reset,
    input [31:0] PC_in,
    output reg [31:0] PC_out
);

always @(posedge clk or posedge reset)
begin
    if (reset)
        PC_out <= 0;
    else
        PC_out <= PC_in;
end

endmodule

Labs/instruction_fetch.v
`timescale 1ns / 1ps

module instruction_fetch(
    input clk,
    input reset,
    output [31:0] instruction
);

wire [31:0] PC_current;
wire [31:0] PC_next;

// PC
PC pc1 (
    .clk(clk),
    .reset(reset),
    .PC_in(PC_next),
    .PC_out(PC_current)
);

// Adder (PC + 4)
adder add1 (
    .a(PC_current),
    .b(32'd4),
    .sum(PC_next)
);

// Instruction Memory
inst_mem imem (
    .PC(PC_current),
    .reset(reset),
    .Instruction_Code(instruction)
);

endmodule

Labs/instruction_fetch_tb.v
`timescale 1ns / 1ps

module instruction_fetch_tb;

reg clk;
reg reset;
wire [31:0] instruction;

instruction_fetch uut (
    .clk(clk),
    .reset(reset),
    .instruction(instruction)
);

// Clock
always #10 clk = ~clk;

initial
begin
    $dumpfile("if.vcd");
    $dumpvars(0, instruction_fetch_tb);

    clk = 0;
    reset = 1;

    #20 reset = 0;

    #200 $finish;
end

initial
begin
    $monitor("Time=%0t | Instruction=%h", $time, instruction);
end

endmodule

Labs/if.vcd
$date
	Thu Apr  2 09:49:26 2026
$end
$version
	Icarus Verilog
$end
$timescale
	1ps
$end
$scope module instruction_fetch_tb $end
$var wire 32 ! instruction [31:0] $end
$var reg 1 " clk $end
$var reg 1 # reset $end
$scope module uut $end
$var wire 1 " clk $end
$var wire 1 # reset $end
$var wire 32 $ instruction [31:0] $end
$var wire 32 % PC_next [31:0] $end
$var wire 32 & PC_current [31:0] $end
$scope module add1 $end
$var wire 32 ' b [31:0] $end
$var wire 32 ( sum [31:0] $end
$var wire 32 ) a [31:0] $end
$upscope $end
$scope module imem $end
$var wire 1 # reset $end
$var wire 32 * PC [31:0] $end
$var wire 32 + Instruction_Code [31:0] $end
$upscope $end
$scope module pc1 $end
$var wire 32 , PC_in [31:0] $end
$var wire 1 " clk $end
$var wire 1 # reset $end
$var reg 32 - PC_out [31:0] $end
$upscope $end
$upscope $end
$upscope $end
$enddefinitions $end
$comment Show the parameter values. $end
$dumpall
$end
#0
$dumpvars
b0 -
b100 ,
b100101000000001100110011 +
b0 *
b0 )
b100 (
b100 '
b0 &
b100 %
b100101000000001100110011 $
1#
0"
b100101000000001100110011 !
$end
#10000
1"
#20000
0"
0#
#30000
b1000001001110010000001110110011 !
b1000001001110010000001110110011 $
b1000001001110010000001110110011 +
b1000 %
b1000 (
b1000 ,
b100 &
b100 )
b100 *
b100 -
1"
#40000
0"
#50000
b11010110100000001010110011 !
b11010110100000001010110011 $
b11010110100000001010110011 +
b1100 %
b1100 (
b1100 ,
b1000 &
b1000 )
b1000 *
b1000 -
1"
#60000
0"
#70000
b1011110110100111000110011 !
b1011110110100111000110011 $
b1011110110100111000110011 +
b10000 %
b10000 (
b10000 ,
b1100 &
b1100 )
b1100 *
b1100 -
1"
#80000
0"
#90000
b1100111000001111010110011 !
b1100111000001111010110011 $
b1100111000001111010110011 +
b10100 %
b10100 (
b10100 ,
b10000 &
b10000 )
b10000 *
b10000 -
1"
#100000
0"
#110000
b1101111010101111100110011 !
b1101111010101111100110011 $
b1101111010101111100110011 +
b11000 %
b11000 (
b11000 ,
b10100 &
b10100 )
b10100 *
b10100 -
1"
#120000
0"
#130000
b110101100111111110110011 !
b110101100111111110110011 $
b110101100111111110110011 +
b11100 %
b11100 (
b11100 ,
b11000 &
b11000 )
b11000 *
b11000 -
1"
#140000
0"
#150000
b111101110110100010110011 !
b111101110110100010110011 $
b111101110110100010110011 +
b100000 %
b100000 (
b100000 ,
b11100 &
b11100 )
b11100 *
b11100 -
1"
#160000
0"
#170000
bx !
bx $
bx +
b100100 %
b100100 (
b100100 ,
b100000 &
b100000 )
b100000 *
b100000 -
1"
#180000
0"
#190000
b101000 %
b101000 (
b101000 ,
b100100 &
b100100 )
b100100 *
b100100 -
1"
#200000
0"
#210000
b101100 %
b101100 (
b101100 ,
b101000 &
b101000 )
b101000 *
b101000 -
1"
