Labs/memory_32x32.v
module memory_32x32 (
    input clk,
    input [4:0] addr,          // 5-bit address (0–31)
    output reg [31:0] data_out // 32-bit output
);

    reg [31:0] mem [31:0];     // 32 registers of 32 bits
    integer i;

    // Initialize memory: mem[i] = i
    initial begin
        for (i = 0; i < 32; i = i + 1) begin
            mem[i] = i;
        end
    end

    // Read on positive clock edge
    always @(posedge clk) begin
        data_out <= mem[addr];
    end

endmodule

Labs/memory_32x32_tb.v
`timescale 1ns/1ps

module memory_32x32_tb;

    reg clk;
    reg [4:0] addr;
    wire [31:0] data_out;

    // Instantiate DUT
    memory_32x32 uut (
        .clk(clk),
        .addr(addr),
        .data_out(data_out)
    );

    // Clock generation
    always #5 clk = ~clk;

    initial begin
        // Dump file setup
        $dumpfile("memory_32x32.vcd");
        $dumpvars(0, memory_32x32_tb);

        // Initialize
        clk = 0;
        addr = 0;

        // Test cases
        #10 addr = 5'd0;
        #10 addr = 5'd4;
        #10 addr = 5'd8;
        #10 addr = 5'd16;
        #10 addr = 5'd31;

        #20 $finish;
    end

endmodule

Labs/memory_32x32.vcd
$date
	Mon Apr  6 14:55:10 2026
$end
$version
	Icarus Verilog
$end
$timescale
	1ps
$end
$scope module memory_32x32_tb $end
$var wire 32 ! data_out [31:0] $end
$var reg 5 " addr [4:0] $end
$var reg 1 # clk $end
$scope module uut $end
$var wire 5 $ addr [4:0] $end
$var wire 1 # clk $end
$var reg 32 % data_out [31:0] $end
$var integer 32 & i [31:0] $end
$upscope $end
$upscope $end
$enddefinitions $end
$comment Show the parameter values. $end
$dumpall
$end
#0
$dumpvars
b100000 &
bx %
b0 $
0#
b0 "
bx !
$end
#5000
b0 !
b0 %
1#
#10000
0#
#15000
1#
#20000
0#
b100 "
b100 $
#25000
b100 !
b100 %
1#
#30000
0#
b1000 "
b1000 $
#35000
b1000 !
b1000 %
1#
#40000
0#
b10000 "
b10000 $
#45000
b10000 !
b10000 %
1#
#50000
0#
b11111 "
b11111 $
#55000
b11111 !
b11111 %
1#
